dymax/__init__.py
dymax/constants.py
dymax/convert.py
dymax/examples.py
dymax/io.py
dymax/data/bmng.jpg
dymax/data/etopo1.jpg
dymax/data/gshhs_c.xz
dymax/data/gshhs_f.xz
dymax/data/gshhs_h.xz
dymax/data/gshhs_i.xz
dymax/data/gshhs_l.xz
dymax-1.1.3.dist-info/LICENSE
dymax-1.1.3.dist-info/METADATA
dymax-1.1.3.dist-info/WHEEL
dymax-1.1.3.dist-info/top_level.txt
dymax-1.1.3.dist-info/RECORD
