Metadata-Version: 2.1
Name: dymax
Version: 1.1.3
Summary: Dymaxion Fuller Projection Utilities
Home-page: https://github.com/Teque5/pydymax
Author: Teque5
Maintainer: Teque5
License: Attribution-NonCommercial-ShareAlike 4.0 International (CC BY-NC-SA 4.0)
Platform: UNKNOWN
Classifier: Programming Language :: Python :: 3
Classifier: Topic :: Scientific/Engineering :: GIS
Classifier: Topic :: Scientific/Engineering :: Visualization
License-File: LICENSE
Requires-Dist: Pillow
Requires-Dist: matplotlib
Requires-Dist: numba
Requires-Dist: numpy
